oneiot_scheduler/__init__.py
oneiot_scheduler-0.0.1.data/scripts/iot-schedule
oneiot_scheduler-0.0.1.dist-info/LICENSE
oneiot_scheduler-0.0.1.dist-info/METADATA
oneiot_scheduler-0.0.1.dist-info/WHEEL
oneiot_scheduler-0.0.1.dist-info/top_level.txt
oneiot_scheduler-0.0.1.dist-info/RECORD
