Metadata-Version: 2.1
Name: oneiot-scheduler
Version: 0.0.1
Summary: OneIoT Scheduler
Home-page: https://github.com/lirwin3007/OneIoT-Scheduler
Author: Louis Irwin
Author-email: coding@louisirwin.co.uk
License: UNKNOWN
Platform: UNKNOWN
Requires-Python: >=3.6
Requires-Dist: oneiot-core
Requires-Dist: apscheduler
